artellapipe/__init__.py
artellapipe/__version__.py
artellapipe/config.json
artellapipe/menu.json
artellapipe/shelf.json
artellapipe/version.json
artellapipe/core/__init__.py
artellapipe/core/artellaclasses.py
artellapipe/core/artellalib.py
artellapipe/core/defines.py
artellapipe/core/project.py
artellapipe/gui/__init__.py
artellapipe/gui/tray.py
artellapipe/gui/window.py
artellapipe/resources/icons/color/artella.png
artellapipe-0.0.1.dist-info/LICENSE
artellapipe-0.0.1.dist-info/METADATA
artellapipe-0.0.1.dist-info/WHEEL
artellapipe-0.0.1.dist-info/top_level.txt
artellapipe-0.0.1.dist-info/RECORD
