Metadata-Version: 2.1
Name: artellapipe
Version: 0.0.1
Summary: Framework to create generic Artella based pipelines
Home-page: https://github.com/tpoveda/artellapipe
Author: Tomas Poveda
Author-email: tpovedatd@gmail.com
License: MIT
Platform: UNKNOWN
Provides-Extra: dev
Requires-Dist: wheel ; extra == 'dev'
Provides-Extra: test
Requires-Dist: pytest ; extra == 'test'
